<?xml version="1.0" encoding="utf-8"?>
<scene>
    <group name="group1">
        <lod name="cows" maxDistance="5000">
            <geometry name="cow_1" path="models/cows/cow_0.99.obj"/>
            <geometry name="cow_2" path="models/cows/cow_0.5.obj"/>
            <geometry name="cow_3" path="models/cows/cow_0.3.obj"/>
            <geometry name="cow_4" path="models/cows/cow_0.1.obj"/>
            <geometry name="cow_5" path="models/cows/cow_0.05.obj"/>
            <geometry name="cow_6" path="models/cows/cow_0.01.obj"/>
        </lod>
    </group>
</scene>
